digital_blocks/decoder/des.v
module dec1x2(a, en, y0, y1);
    input a, en;
    output y0, y1;
    and A1(y0, ~a, en);
    and A2(y1, a, en);
endmodule
module dec2x4(a, b, en, y0, y1, y2, y3);
    input a, b, en;
    output y0, y1, y2, y3;
    wire p, q;
    // p = a'e, q = ae
    dec1x2 D1(a, en, p, q);
    dec1x2 D2(b, p, y0, y1);
    dec1x2 D3(b, q, y2, y3);
endmodule
module dec3x8(a, b, c, y0, y1, y2, y3, y4, y5, y6, y7);
    input a, b, c;
    output y0, y1, y2, y3, y4, y5, y6, y7;
    //ive used a, ~a as enable in 3x8 decoder using 2x4 decoders
    dec2x4 D1(b, c, ~a, y0, y1, y2, y3);    // ~a is enable
    dec2x4 D2(b, c, a, y4, y5, y6, y7);     // a is enable
endmodule

digital_blocks/decoder/tb.v
module dec1x2_test;
    reg a, en;
    wire y0, y1;
    dec1x2 uut (
        .a(a), .en(en),
        .y0(y0), .y1(y1)
    );
    initial begin 
        $dumpfile("dec1x2_test.vcd");
        $dumpvars(0, dec1x2_test);
        a = 1'b0;
        en = 1'b0;
        #200 $finish;
    end
    always #10 a = ~a;
    always #20 en = ~en;
    initial begin 
        $monitor("time = %t \t a = %b \ t en = %b \t y0 = %b \t y1 = %b", $time, a, en, y0, y1);
    end
endmodule
module dec2x4_test;
    reg a, b, en;
    wire y0, y1, y2, y3;
    dec2x4 uut (
        .a(a), .b(b), .en(en),
        .y0(y0), .y1(y1), .y2(y2), .y3(y3)
    );
    initial begin 
        $dumpfile("dec2x4_test.vcd");
        $dumpvars(0, dec2x4_test);
        a = 1'b0;
        b = 1'b0;
        en = 1'b0;
        #200 $finish;
    end
    always #20 a = ~a;
    always #10 b = ~b;
    always #40 en = ~en;
    initial begin 
        $monitor("time = %t \t a = %b \ t b = %b \t en = %b \t y0 = %b \t y1 = %b \t y2 = %b \t y3 = %b", $time, a, b, en, y0, y1, y2, y3);
    end
endmodule
module dec3x8_test;
    reg a, b, c;
    wire y0, y1, y2, y3, y4, y5, y6, y7;
    dec3x8 uut (
        .a(a), .b(b), .c(c),
        .y0(y0), .y1(y1), .y2(y2), .y3(y3),
        .y4(y4), .y5(y5), .y6(y6), .y7(y7)
    );
    initial begin 
        $dumpfile("dec3x8_test.vcd");
        $dumpvars(0, dec3x8_test);
        a = 1'b0;
        b = 1'b0;
        c = 1'b0;
        #200 $finish;
    end
    always #40 a = ~a;
    always #20 b = ~b;
    always #10 c = ~c;
    initial begin 
        $monitor("time = %t \t a = %b \ t b = %b \t c = %b \t y0 = %b \t y1 = %b \t y2 = %b \t y3 = %b \t y4 = %b \t y5 = %b \t y6 = %b \t y7 = %b", $time, a, b, c, y0, y1, y2, y3, y4, y5, y6, y7);
    end
endmodule

digital_blocks/decoder/dec1x2_test.vcd
$date
	Wed Oct  2 01:27:45 2024
$end
$version
	Icarus Verilog
$end
$timescale
	1s
$end
$scope module dec1x2_test $end
$var wire 1 ! y1 $end
$var wire 1 " y0 $end
$var reg 1 # a $end
$var reg 1 $ en $end
$scope module uut $end
$var wire 1 # a $end
$var wire 1 $ en $end
$var wire 1 " y0 $end
$var wire 1 ! y1 $end
$upscope $end
$upscope $end
$scope module dec2x4_test $end
$var wire 1 % y3 $end
$var wire 1 & y2 $end
$var wire 1 ' y1 $end
$var wire 1 ( y0 $end
$var reg 1 ) a $end
$var reg 1 * b $end
$var reg 1 + en $end
$scope module uut $end
$var wire 1 ) a $end
$var wire 1 * b $end
$var wire 1 + en $end
$var wire 1 % y3 $end
$var wire 1 & y2 $end
$var wire 1 ' y1 $end
$var wire 1 ( y0 $end
$var wire 1 , q $end
$var wire 1 - p $end
$scope module D1 $end
$var wire 1 ) a $end
$var wire 1 + en $end
$var wire 1 - y0 $end
$var wire 1 , y1 $end
$upscope $end
$scope module D2 $end
$var wire 1 * a $end
$var wire 1 - en $end
$var wire 1 ( y0 $end
$var wire 1 ' y1 $end
$upscope $end
$scope module D3 $end
$var wire 1 * a $end
$var wire 1 , en $end
$var wire 1 & y0 $end
$var wire 1 % y1 $end
$upscope $end
$upscope $end
$upscope $end
$scope module dec3x8_test $end
$var wire 1 . y7 $end
$var wire 1 / y6 $end
$var wire 1 0 y5 $end
$var wire 1 1 y4 $end
$var wire 1 2 y3 $end
$var wire 1 3 y2 $end
$var wire 1 4 y1 $end
$var wire 1 5 y0 $end
$var reg 1 6 a $end
$var reg 1 7 b $end
$var reg 1 8 c $end
$scope module uut $end
$var wire 1 6 a $end
$var wire 1 7 b $end
$var wire 1 8 c $end
$var wire 1 . y7 $end
$var wire 1 / y6 $end
$var wire 1 0 y5 $end
$var wire 1 1 y4 $end
$var wire 1 2 y3 $end
$var wire 1 3 y2 $end
$var wire 1 4 y1 $end
$var wire 1 5 y0 $end
$scope module D1 $end
$var wire 1 7 a $end
$var wire 1 8 b $end
$var wire 1 9 en $end
$var wire 1 2 y3 $end
$var wire 1 3 y2 $end
$var wire 1 4 y1 $end
$var wire 1 5 y0 $end
$var wire 1 : q $end
$var wire 1 ; p $end
$scope module D1 $end
$var wire 1 7 a $end
$var wire 1 9 en $end
$var wire 1 ; y0 $end
$var wire 1 : y1 $end
$upscope $end
$scope module D2 $end
$var wire 1 8 a $end
$var wire 1 ; en $end
$var wire 1 5 y0 $end
$var wire 1 4 y1 $end
$upscope $end
$scope module D3 $end
$var wire 1 8 a $end
$var wire 1 : en $end
$var wire 1 3 y0 $end
$var wire 1 2 y1 $end
$upscope $end
$upscope $end
$scope module D2 $end
$var wire 1 7 a $end
$var wire 1 8 b $end
$var wire 1 6 en $end
$var wire 1 . y3 $end
$var wire 1 / y2 $end
$var wire 1 0 y1 $end
$var wire 1 1 y0 $end
$var wire 1 < q $end
$var wire 1 = p $end
$scope module D1 $end
$var wire 1 7 a $end
$var wire 1 6 en $end
$var wire 1 = y0 $end
$var wire 1 < y1 $end
$upscope $end
$scope module D2 $end
$var wire 1 8 a $end
$var wire 1 = en $end
$var wire 1 1 y0 $end
$var wire 1 0 y1 $end
$upscope $end
$scope module D3 $end
$var wire 1 8 a $end
$var wire 1 < en $end
$var wire 1 / y0 $end
$var wire 1 . y1 $end
$upscope $end
$upscope $end
$upscope $end
$upscope $end
$enddefinitions $end
$comment Show the parameter values. $end
$dumpall
$end
#0
$dumpvars
0=
0<
1;
0:
19
08
07
06
15
04
03
02
01
00
0/
0.
0-
0,
0+
0*
0)
0(
0'
0&
0%
0$
0#
0"
0!
$end
#10
05
14
18
1*
1#
#20
1"
0;
13
04
1:
08
0*
0#
17
1)
1$
#30
03
0"
12
1!
18
1*
1#
#40
11
1(
1=
1-
02
0:
0!
09
08
0*
0#
07
0)
0$
16
1+
#50
01
0(
10
1'
18
1*
1#
#60
1"
0=
1/
0-
1&
00
0'
1<
1,
08
0*
0#
17
1)
1$
#70
0/
0&
0"
1.
1%
1!
18
1*
1#
#80
15
1;
0.
0%
0!
19
0<
0,
08
0*
0#
07
0)
0$
06
0+
#90
05
14
18
1*
1#
#100
1"
0;
13
04
1:
08
0*
0#
17
1)
1$
#110
03
0"
12
1!
18
1*
1#
#120
11
1(
1=
1-
02
0:
0!
09
08
0*
0#
07
0)
0$
16
1+
#130
01
0(
10
1'
18
1*
1#
#140
1"
0=
1/
0-
1&
00
0'
1<
1,
08
0*
0#
17
1)
1$
#150
0/
0&
0"
1.
1%
1!
18
1*
1#
#160
15
1;
0.
0%
0!
19
0<
0,
08
0*
0#
07
0)
0$
06
0+
#170
05
14
18
1*
1#
#180
1"
0;
13
04
1:
08
0*
0#
17
1)
1$
#190
03
0"
12
1!
18
1*
1#
#200
11
1(
1=
1-
02
0:
0!
09
08
0*
0#
07
0)
0$
16
1+
