primitive_gates/des.v
module des(a, b, y_and, y_or, y_nor, y_nand, y_xor, y_not, y_xnor);
    input a,b;
    output y_and, y_or, y_nor, y_nand, y_xor, y_not, y_xnor;

    and A1(y_and, a, b);
    or A2(y_or, a, b);

    nor A3(y_nor, a, b);
    nand A4(y_nand, a, b);

    xor A5(y_xor, a, b);
    xnor A6(y_xnor, a, b);

    not A7(y_not, a);

endmodule

primitive_gates/tb.v
module tb;
    reg a;
    reg b;
    wire y_and, y_or, y_nor, y_nand, y_xor, y_not, y_xnor;

    des uut (
        .a(a), .b(b),
        .y_and(y_and), .y_or(y_or),
        .y_nor(y_nor), .y_nand(y_nand),
        .y_xor(y_xor), .y_xnor(y_xnor),
        .y_not(y_not)
    );

    initial begin
        $dumpfile("tb.vcd");
        $dumpvars(0, tb);
        
        a = 1'b0;
        b = 1'b0;
        #50;
        $finish;
    end

    always #5 a = ~a;
    always #10 b = ~b;
    always@(a)
        $monitor("time = %t \t y_and = %d \t y_or = %d \t y_nor = %d \t y_nand = %d \t y_xor = %d \t y_not = %d \t y_xnor = %d", $time, y_and, y_or, y_nor, y_nand, y_xor, y_not, y_xnor);

endmodule

primitive_gates/tb.vcd
$date
	Tue Oct  1 03:14:21 2024
$end
$version
	Icarus Verilog
$end
$timescale
	1s
$end
$scope module tb $end
$var wire 1 ! y_xor $end
$var wire 1 " y_xnor $end
$var wire 1 # y_or $end
$var wire 1 $ y_not $end
$var wire 1 % y_nor $end
$var wire 1 & y_nand $end
$var wire 1 ' y_and $end
$var reg 1 ( a $end
$var reg 1 ) b $end
$scope module uut $end
$var wire 1 ( a $end
$var wire 1 ) b $end
$var wire 1 ' y_and $end
$var wire 1 & y_nand $end
$var wire 1 % y_nor $end
$var wire 1 $ y_not $end
$var wire 1 # y_or $end
$var wire 1 " y_xnor $end
$var wire 1 ! y_xor $end
$upscope $end
$upscope $end
$enddefinitions $end
$comment Show the parameter values. $end
$dumpall
$end
#0
$dumpvars
0)
0(
0'
1&
1%
1$
0#
1"
0!
$end
#5
1#
0%
1!
0"
0$
1(
#10
1$
0(
1)
#15
1'
0&
0!
1"
0$
1(
#20
1$
0'
0#
1%
1&
0(
0)
#25
1#
0%
1!
0"
0$
1(
#30
1$
0(
1)
#35
1'
0&
0!
1"
0$
1(
#40
1$
0'
0#
1%
1&
0(
0)
#45
1#
0%
1!
0"
0$
1(
#50
1$
0(
1)
