digital_blocks/demux/des.v
module demux2(a, s, y0, y1);
    input a,s;
    output y0, y1;
    and A1(y0, a, ~s);
    and A2(y1, a, s);
endmodule
module demux4(a, s1, s0, y0, y1, y2, y3);
    input a, s1, s0;
    output y0, y1, y2, y3;
    wire p, q;
    demux2 D1(a, s1, p, q);
    demux2 D2(p, s0, y0, y1);
    demux2 D3(q, s0, y2, y3);
endmodule
module demux8(a, s0, s1, s2, y0, y1, y2, y3, y4, y5, y6, y7);
    input a, s2, s1, s0;
    output y0, y1, y2, y3, y4, y5, y6, y7;
    demux2 D1(a, s2, p, q);
    demux4 D2(p, s1, s0, y0, y1, y2, y3);
    demux4 D3(q, s1, s0, y4, y5, y6, y7);
endmodule

digital_blocks/demux/tb.v
module demux2_test;
    reg a, s;
    wire y0, y1;
    demux2 uut(
        .a(a), .s(s),
        .y0(y0), .y1(y1)
    );
    initial begin 
        $dumpfile("demux2_test.vcd");
        $dumpvars(0, demux2_test);
        a = 0;
        s = 0;
        #100
        $finish;
    end
    always #10 a = ~a;
    always #5 s = ~s;
    initial begin 
        $monitor("time = %t \t a = %b \t s = %b \t y0 = %b \t y1 = %b", $time, a, s, y0, y1);
    end
endmodule
module demux4_test;
    reg a, s1, s0;
    wire y0, y1, y2, y3;
    demux4 uut(
        .a(a), .s0(s0), .s1(s1),
        .y0(y0), .y1(y1),
        .y2(y2), .y3(y3)
    );
    initial begin 
        $dumpfile("demux4_test.vcd");
        $dumpvars(0, demux4_test);
        a = 0;
        s0 = 0;
        s1 = 0;
        #200
        $finish;
    end
    always #20 a = ~a;
    always #5 s0 = ~s0;
    always #10 s1 = ~s1;
    initial begin 
        $monitor("time = %t \t a = %b \t s0 = %b \t s1 = %b \t y0 = %b \t y1 = %b \t y2 = %b \t y3 = %b", $time, a, s0, s1, y0, y1, y2, y3);
    end
endmodule
module demux8_test;
    reg a, s2, s1, s0;
    wire y0, y1, y2, y3, y4, y5, y6, y7;
    demux8 uut(
        .a(a), .s0(s0), .s1(s1), .s2(s2),
        .y0(y0), .y1(y1), .y2(y2), .y3(y3),
        .y4(y4), .y5(y5), .y6(y6), .y7(y7)
    );
    initial begin 
        $dumpfile("demux8_test.vcd");
        $dumpvars(0, demux8_test);
        a = 0;
        s0 = 0;
        s1 = 0;
        s2 = 0;
        #400
        $finish;
    end
    always #40 a = ~a;
    always #5 s0 = ~s0;
    always #10 s1 = ~s1;
    always #20 s2 = ~s2;
    initial begin 
        $monitor("time = %t \t a = %b \t s0 = %b \t s1 = %b \t s2 = %b \t y0 = %b \t y1 = %b \t y2 = %b \t y3 = %b \t y4 = %b \t y5 = %b \t y6 = %b \t y7 = %b", $time, a, s0, s1, s2, y0, y1, y2, y3, y4, y5, y6, y7);
    end
endmodule

digital_blocks/demux/demux2_test.vcd
$date
	Wed Oct  2 01:40:29 2024
$end
$version
	Icarus Verilog
$end
$timescale
	1s
$end
$scope module demux2_test $end
$var wire 1 ! y1 $end
$var wire 1 " y0 $end
$var reg 1 # a $end
$var reg 1 $ s $end
$scope module uut $end
$var wire 1 # a $end
$var wire 1 $ s $end
$var wire 1 " y0 $end
$var wire 1 ! y1 $end
$upscope $end
$upscope $end
$scope module demux4_test $end
$var wire 1 % y3 $end
$var wire 1 & y2 $end
$var wire 1 ' y1 $end
$var wire 1 ( y0 $end
$var reg 1 ) a $end
$var reg 1 * s0 $end
$var reg 1 + s1 $end
$scope module uut $end
$var wire 1 ) a $end
$var wire 1 * s0 $end
$var wire 1 + s1 $end
$var wire 1 % y3 $end
$var wire 1 & y2 $end
$var wire 1 ' y1 $end
$var wire 1 ( y0 $end
$var wire 1 , q $end
$var wire 1 - p $end
$scope module D1 $end
$var wire 1 ) a $end
$var wire 1 + s $end
$var wire 1 - y0 $end
$var wire 1 , y1 $end
$upscope $end
$scope module D2 $end
$var wire 1 - a $end
$var wire 1 * s $end
$var wire 1 ( y0 $end
$var wire 1 ' y1 $end
$upscope $end
$scope module D3 $end
$var wire 1 , a $end
$var wire 1 * s $end
$var wire 1 & y0 $end
$var wire 1 % y1 $end
$upscope $end
$upscope $end
$upscope $end
$scope module demux8_test $end
$var wire 1 . y7 $end
$var wire 1 / y6 $end
$var wire 1 0 y5 $end
$var wire 1 1 y4 $end
$var wire 1 2 y3 $end
$var wire 1 3 y2 $end
$var wire 1 4 y1 $end
$var wire 1 5 y0 $end
$var reg 1 6 a $end
$var reg 1 7 s0 $end
$var reg 1 8 s1 $end
$var reg 1 9 s2 $end
$scope module uut $end
$var wire 1 6 a $end
$var wire 1 7 s0 $end
$var wire 1 8 s1 $end
$var wire 1 9 s2 $end
$var wire 1 . y7 $end
$var wire 1 / y6 $end
$var wire 1 0 y5 $end
$var wire 1 1 y4 $end
$var wire 1 2 y3 $end
$var wire 1 3 y2 $end
$var wire 1 4 y1 $end
$var wire 1 5 y0 $end
$var wire 1 : q $end
$var wire 1 ; p $end
$scope module D1 $end
$var wire 1 6 a $end
$var wire 1 9 s $end
$var wire 1 ; y0 $end
$var wire 1 : y1 $end
$upscope $end
$scope module D2 $end
$var wire 1 ; a $end
$var wire 1 7 s0 $end
$var wire 1 8 s1 $end
$var wire 1 2 y3 $end
$var wire 1 3 y2 $end
$var wire 1 4 y1 $end
$var wire 1 5 y0 $end
$var wire 1 < q $end
$var wire 1 = p $end
$scope module D1 $end
$var wire 1 ; a $end
$var wire 1 8 s $end
$var wire 1 = y0 $end
$var wire 1 < y1 $end
$upscope $end
$scope module D2 $end
$var wire 1 = a $end
$var wire 1 7 s $end
$var wire 1 5 y0 $end
$var wire 1 4 y1 $end
$upscope $end
$scope module D3 $end
$var wire 1 < a $end
$var wire 1 7 s $end
$var wire 1 3 y0 $end
$var wire 1 2 y1 $end
$upscope $end
$upscope $end
$scope module D3 $end
$var wire 1 : a $end
$var wire 1 7 s0 $end
$var wire 1 8 s1 $end
$var wire 1 . y3 $end
$var wire 1 / y2 $end
$var wire 1 0 y1 $end
$var wire 1 1 y0 $end
$var wire 1 > q $end
$var wire 1 ? p $end
$scope module D1 $end
$var wire 1 : a $end
$var wire 1 8 s $end
$var wire 1 ? y0 $end
$var wire 1 > y1 $end
$upscope $end
$scope module D2 $end
$var wire 1 ? a $end
$var wire 1 7 s $end
$var wire 1 1 y0 $end
$var wire 1 0 y1 $end
$upscope $end
$scope module D3 $end
$var wire 1 > a $end
$var wire 1 7 s $end
$var wire 1 / y0 $end
$var wire 1 . y1 $end
$upscope $end
$upscope $end
$upscope $end
$upscope $end
$enddefinitions $end
$comment Show the parameter values. $end
$dumpall
$end
#0
$dumpvars
0?
0>
0=
0<
0;
0:
09
08
07
06
05
04
03
02
01
00
0/
0.
0-
0,
0+
0*
0)
0(
0'
0&
0%
0$
0#
0"
0!
$end
#5
17
1*
1$
#10
1"
07
0*
0$
18
1+
1#
#15
0"
1!
17
1*
1$
#20
1(
1-
0!
07
0*
0$
08
0+
0#
19
1)
#25
0(
1'
17
1*
1$
#30
1"
0-
1&
0'
1,
07
0*
0$
18
1+
1#
#35
0&
0"
1%
1!
17
1*
1$
#40
15
1=
1;
0%
0!
0,
07
0*
0$
08
0+
0#
09
0)
16
#45
05
14
17
1*
1$
#50
1"
0=
13
04
1<
07
0*
0$
18
1+
1#
#55
03
0"
12
1!
17
1*
1$
#60
11
1(
1-
0;
1?
02
0<
0!
1:
07
0*
0$
08
0+
0#
19
1)
#65
01
0(
10
1'
17
1*
1$
#70
1"
0?
1/
0-
1&
00
0'
1>
1,
07
0*
0$
18
1+
1#
#75
0/
0&
0"
1.
1%
1!
17
1*
1$
#80
0.
0%
0>
0!
0,
0:
07
0*
0$
08
0+
0#
09
0)
06
#85
17
1*
1$
#90
1"
07
0*
0$
18
1+
1#
#95
0"
1!
17
1*
1$
#100
1(
1-
0!
07
0*
0$
08
0+
0#
19
1)
