digital_blocks/des.v
///// mux
module mux2(a, b, s, y);
    input a, b, s;
    output y;
    wire y1, y2;
    and A1(y1, a, ~s);
    and A2(y2, b, s);
    //as'+bs
    or A3(y, y1, y2);
endmodule
module mux4(a0, a1, a2, a3, s0, s1, y);
    input a0, a1, a2, a3, s0, s1;
    output y;
    wire y1, y2;
    mux2 A1(a0, a1, s0, y1);
    mux2 A2(a2, a3, s0, y2);
    mux2 A3(y1, y2, s1, y);

endmodule
module mux8(a0, a1, a2, a3, a4, a5, a6, a7, s0, s1, s2, y);
    input a0, a1, a2, a3, a4, a5, a6, a7, s0, s1, s2;
    output y;
    wire y1, y2;
    mux4 A1(a0, a1, a2, a3, s0, s1, y1);
    mux4 A2(a4, a5, a6, a7, s0, s1, y2);
    mux2 A3(y1, y2, s2, y);
endmodule


///// demux
module demux2(a, s, y0, y1);
    input a,s;
    output y0, y1;
    and A1(y0, a, ~s);
    and A2(y1, a, s);
endmodule
module demux4(a, s0, s1, y0, y1, y2, y3);
    input a, s1, s0;
    output y0, y1, y2, y3;
    and A1(y0, a, ~s0, ~s1);
    and A2(y1, a, s0, ~s1);
    and A3(y2, a, ~s0, s1);
    and A4(y3, a, s0, s1);
endmodule
module demux8(a, s0, s1, s2, y0, y1, y2, y3, y4, y5, y6, y7);
    input a, s2, s1, s0;
    output y0, y1, y2, y3, y4, y5, y6, y7;
    and A7(y0, a, ~s0, ~s1, ~s2);
    and A6(y1, a, s0, ~s1, ~s2);
    and A5(y2, a, ~s0, s1, ~s2);
    and A4(y3, a, s0, s1, ~s2);
    and A3(y4, a, ~s0, ~s1, s2);
    and A2(y5, a, s0, ~s1, s2);
    and A1(y6, a, ~s0, s1, s2);
    and A0(y7, a, s0, s1, s2);
endmodule


//// decoder
module dec1x2(a, en, y0, y1);
    input a, en;
    output y0, y1;
    and A1(y0, ~a, en);
    and A2(y1, a, en);
endmodule
module dec2x4(a, b, en, y0, y1, y2, y3);
    input a, b, en;
    output y0, y1, y2, y3;
    wire p, q;
    // p = a'e, q = ae
    dec1x2 D1(a, en, p, q);
    dec1x2 D2(b, p, y0, y1);
    dec1x2 D3(b, q, y2, y3);
endmodule
module dec3x8(a, b, c, y0, y1, y2, y3, y4, y5,y6, y7);
    input a, b, c;
    output y0, y1, y2, y3, y4, y5,y6, y7;
    //ive used a, ~a as enable in 3x8 decoder using 2x4 decoders
    dec2x4 D1(b, c, ~a, y0, y1, y2, y3);
    dec2x4 D2(b, c, a, y4, y5, y6, y7);
endmodule

digital_blocks/mux/tb.v
module mux8_test;
reg a0, a1, a2, a3, a4, a5, a6, a7, s0, s1, s2;
wire y;
mux8 uut(
    .a0(a0), .a1(a1), .a2(a2), .a3(a3),
    .a4(a4), .a5(a5), .a6(a6), .a7(a7),
    .s0(s0), .s1(s1), .s2(s2),
    .y(y)
);
initial begin 
    $dumpfile("mux8_test.vcd");
    $dumpvars(0, mux8_test);
    a0 = 1'b1; a1 = 1'b0; a2 = 1'b1; a3 = 1'b0;
    a4 = 1'b1; a5 = 1'b1; a6 = 1'b0; a7 = 1'b0;
    s0 = 1'b0; s1 = 1'b0; s2 = 1'b0;
    // checking all the eight possible outcomes
    #0 s0 = 1'b0; s1 = 1'b0; s2 = 1'b0;
    #20 s0 = 1'b1; s1 = 1'b0; s2 = 1'b0;
    #20 s0 = 1'b0; s1 = 1'b1; s2 = 1'b0;
    #20 s0 = 1'b1; s1 = 1'b1; s2 = 1'b0;
    #20 s0 = 1'b0; s1 = 1'b0; s2 = 1'b1;
    #20 s0 = 1'b1; s1 = 1'b0; s2 = 1'b1;
    #20 s0 = 1'b0; s1 = 1'b1; s2 = 1'b1;
    #20 s0 = 1'b1; s1 = 1'b1; s2 = 1'b1;
    #20
    $finish;
end
initial begin 
    $monitor("time = %t \t a0 = %b \t a1 = %b \t a2 = %b \t a3 = %b \t a4 = %b \t a5 = %b \t a6 = %b \t a7 = %b \t s0 = %b \t s1 = %b \t s2 = %b \t y = %b", $time, a0, a1, a2, a3, a4, a5, a6, a7, s0, s1, s2, y);
end
endmodule
module mux4_test;
reg a0, a1, a2, a3, s0, s1;
wire y;
mux4 uut(
    .a0(a0), .a1(a1), .a2(a2), .a3(a3),
    .s0(s0), .s1(s1),
    .y(y)
);
initial begin 
    $dumpfile("mux4_test.vcd");
    $dumpvars(0, mux4_test);
    a0 = 1'b0; a1 = 1'b1;
    a2 = 1'b0; a3 = 1'b1;
    s0 = 1'b0; s1 = 1'b0;
    #0 s0 = 1'b0; s1 = 1'b0;
    #20 s0 = 1'b0; s1 = 1'b1;
    #20 s0 = 1'b1; s1 = 1'b0;
    #20 s0 = 1'b1; s1 = 1'b1;
    #20
    $finish;
end
initial begin 
    $monitor("time = %t \t a0 = %b \t a1 = %b \t a2 = %b \t a3 = %b \t s0 = %b \t s1 = %b \t y = %b", $time, a0, a1, a2, a3, s0, s1, y);
end
endmodule
module mux2_test;
    reg a, b, s;
    wire y;
    mux2 uut (
        .a(a), .b(b), .s(s),
        .y(y)
    );
    initial begin
        $dumpfile("mux2_test.vcd");
        $dumpvars(0, mux2_test);
        a = 1'b0;
        b = 1'b1;
        s = 1'b0;
        #0 s = 1'b0;
        #50 s = 1'b1;
        #50
        $finish;
    end
    initial begin
        $monitor("time = %t \t a = %b \t b = %b \t s = %b \t y = %b", $time, a, b, s, y);
    end
endmodule

digital_blocks/demux/tb.v
module demux2_test;
    reg a, s;
    wire y0, y1;
    demux2 uut(
        .a(a), .s(s),
        .y0(y0), .y1(y1)
    );
    initial begin 
        $dumpfile("demux2_test.vcd");
        $dumpvars(0, demux2_test);
        a = 0;
        s = 0;
        #100
        $finish;
    end
    always #10 a = ~a;
    always #5 s = ~s;
    initial begin 
        $monitor("time = %t \t a = %b \t s = %b \t y0 = %b \t y1 = %b", $time, a, s, y0, y1);
    end
endmodule
module demux4_test;
    reg a, s1, s0;
    wire y0, y1, y2, y3;
    demux4 uut(
        .a(a), .s0(s0), .s1(s1),
        .y0(y0), .y1(y1),
        .y2(y2), .y3(y3)
    );
    initial begin 
        $dumpfile("demux4_test.vcd");
        $dumpvars(0, demux4_test);
        a = 0;
        s0 = 0;
        s1 = 0;
        #200
        $finish;
    end
    always #20 a = ~a;
    always #5 s0 = ~s0;
    always #10 s1 = ~s1;
    initial begin 
        $monitor("time = %t \t a = %b \t s0 = %b \t s1 = %b \t y0 = %b \t y1 = %b \t y2 = %b \t y3 = %b", $time, a, s0, s1, y0, y1, y2, y3);
    end
endmodule
module demux8_test;
    reg a, s2, s1, s0;
    wire y0, y1, y2, y3, y4, y5, y6, y7;
    demux8 uut(
        .a(a), .s0(s0), .s1(s1), .s2(s2),
        .y0(y0), .y1(y1), .y2(y2), .y3(y3),
        .y4(y4), .y5(y5), .y6(y6), .y7(y7)
    );
    initial begin 
        $dumpfile("demux8_test.vcd");
        $dumpvars(0, demux8_test);
        a = 0;
        s0 = 0;
        s1 = 0;
        s2 = 0;
        #400
        $finish;
    end
    always #40 a = ~a;
    always #5 s0 = ~s0;
    always #10 s1 = ~s1;
    always #20 s2 = ~s2;
    initial begin 
        $monitor("time = %t \t a = %b \t s0 = %b \t s1 = %b \t s2 = %b \t y0 = %b \t y1 = %b \t y2 = %b \t y3 = %b \t y4 = %b \t y5 = %b \t y6 = %b \t y7 = %b", $time, a, s0, s1, s2, y0, y1, y2, y3, y4, y5, y6, y7);
    end
endmodule

digital_blocks/decoder/tb.v
module dec1x2_test;
    reg a, en;
    wire y0, y1;
    dec1x2 uut (
        .a(a), .en(en),
        .y0(y0), .y1(y1)
    );
    initial begin 
        $dumpfile("dec1x2_test.vcd");
        $dumpvars(0, dec1x2_test);
        a = 1'b0;
        en = 1'b0;
        #200 $finish;
    end
    always #10 a = ~a;
    always #20 en = ~en;
    initial begin 
        $monitor("time = %t \t a = %b \ t en = %b \t y0 = %b \t y1 = %b", $time, a, en, y0, y1);
    end
endmodule
module dec2x4_test;
    reg a, b, en;
    wire y0, y1, y2, y3;
    dec2x4 uut (
        .a(a), .b(b), .en(en),
        .y0(y0), .y1(y1), .y2(y2), .y3(y3)
    );
    initial begin 
        $dumpfile("dec2x4_test.vcd");
        $dumpvars(0, dec2x4_test);
        a = 1'b0;
        b = 1'b0;
        en = 1'b0;
        #200 $finish;
    end
    always #20 a = ~a;
    always #10 b = ~b;
    always #40 en = ~en;
    initial begin 
        $monitor("time = %t \t a = %b \ t b = %b \t en = %b \t y0 = %b \t y1 = %b \t y2 = %b \t y3 = %b", $time, a, b, en, y0, y1, y2, y3);
    end
endmodule
module dec3x8_test;
    reg a, b, c;
    wire y0, y1, y2, y3, y4, y5, y6, y7;
    dec3x8 uut (
        .a(a), .b(b), .c(c),
        .y0(y0), .y1(y1), .y2(y2), .y3(y3),
        .y4(y4), .y5(y5), .y6(y6), .y7(y7)
    );
    initial begin 
        $dumpfile("dec3x8_test.vcd");
        $dumpvars(0, dec3x8_test);
        a = 1'b0;
        b = 1'b0;
        c = 1'b0;
        #200 $finish;
    end
    always #40 a = ~a;
    always #20 b = ~b;
    always #10 c = ~c;
    initial begin 
        $monitor("time = %t \t a = %b \ t b = %b \t c = %b \t y0 = %b \t y1 = %b \t y2 = %b \t y3 = %b \t y4 = %b \t y5 = %b \t y6 = %b \t y7 = %b", $time, a, b, c, y0, y1, y2, y3, y4, y5, y6, y7);
    end
endmodule

digital_blocks/dec1x2_test.vcd
$date
	Tue Oct  1 03:17:33 2024
$end
$version
	Icarus Verilog
$end
$timescale
	1s
$end
$scope module dec1x2_test $end
$var wire 1 ! y1 $end
$var wire 1 " y0 $end
$var reg 1 # a $end
$var reg 1 $ en $end
$scope module uut $end
$var wire 1 # a $end
$var wire 1 $ en $end
$var wire 1 " y0 $end
$var wire 1 ! y1 $end
$upscope $end
$upscope $end
$scope module dec2x4_test $end
$var wire 1 % y3 $end
$var wire 1 & y2 $end
$var wire 1 ' y1 $end
$var wire 1 ( y0 $end
$var reg 1 ) a $end
$var reg 1 * b $end
$var reg 1 + en $end
$scope module uut $end
$var wire 1 ) a $end
$var wire 1 * b $end
$var wire 1 + en $end
$var wire 1 % y3 $end
$var wire 1 & y2 $end
$var wire 1 ' y1 $end
$var wire 1 ( y0 $end
$var wire 1 , q $end
$var wire 1 - p $end
$scope module D1 $end
$var wire 1 ) a $end
$var wire 1 + en $end
$var wire 1 - y0 $end
$var wire 1 , y1 $end
$upscope $end
$scope module D2 $end
$var wire 1 * a $end
$var wire 1 - en $end
$var wire 1 ( y0 $end
$var wire 1 ' y1 $end
$upscope $end
$scope module D3 $end
$var wire 1 * a $end
$var wire 1 , en $end
$var wire 1 & y0 $end
$var wire 1 % y1 $end
$upscope $end
$upscope $end
$upscope $end
$scope module dec3x8_test $end
$var wire 1 . y7 $end
$var wire 1 / y6 $end
$var wire 1 0 y5 $end
$var wire 1 1 y4 $end
$var wire 1 2 y3 $end
$var wire 1 3 y2 $end
$var wire 1 4 y1 $end
$var wire 1 5 y0 $end
$var reg 1 6 a $end
$var reg 1 7 b $end
$var reg 1 8 c $end
$scope module uut $end
$var wire 1 6 a $end
$var wire 1 7 b $end
$var wire 1 8 c $end
$var wire 1 . y7 $end
$var wire 1 / y6 $end
$var wire 1 0 y5 $end
$var wire 1 1 y4 $end
$var wire 1 2 y3 $end
$var wire 1 3 y2 $end
$var wire 1 4 y1 $end
$var wire 1 5 y0 $end
$scope module D1 $end
$var wire 1 7 a $end
$var wire 1 8 b $end
$var wire 1 9 en $end
$var wire 1 2 y3 $end
$var wire 1 3 y2 $end
$var wire 1 4 y1 $end
$var wire 1 5 y0 $end
$var wire 1 : q $end
$var wire 1 ; p $end
$scope module D1 $end
$var wire 1 7 a $end
$var wire 1 9 en $end
$var wire 1 ; y0 $end
$var wire 1 : y1 $end
$upscope $end
$scope module D2 $end
$var wire 1 8 a $end
$var wire 1 ; en $end
$var wire 1 5 y0 $end
$var wire 1 4 y1 $end
$upscope $end
$scope module D3 $end
$var wire 1 8 a $end
$var wire 1 : en $end
$var wire 1 3 y0 $end
$var wire 1 2 y1 $end
$upscope $end
$upscope $end
$scope module D2 $end
$var wire 1 7 a $end
$var wire 1 8 b $end
$var wire 1 6 en $end
$var wire 1 . y3 $end
$var wire 1 / y2 $end
$var wire 1 0 y1 $end
$var wire 1 1 y0 $end
$var wire 1 < q $end
$var wire 1 = p $end
$scope module D1 $end
$var wire 1 7 a $end
$var wire 1 6 en $end
$var wire 1 = y0 $end
$var wire 1 < y1 $end
$upscope $end
$scope module D2 $end
$var wire 1 8 a $end
$var wire 1 = en $end
$var wire 1 1 y0 $end
$var wire 1 0 y1 $end
$upscope $end
$scope module D3 $end
$var wire 1 8 a $end
$var wire 1 < en $end
$var wire 1 / y0 $end
$var wire 1 . y1 $end
$upscope $end
$upscope $end
$upscope $end
$upscope $end
$scope module demux2_test $end
$var wire 1 > y1 $end
$var wire 1 ? y0 $end
$var reg 1 @ a $end
$var reg 1 A s $end
$scope module uut $end
$var wire 1 @ a $end
$var wire 1 A s $end
$var wire 1 ? y0 $end
$var wire 1 > y1 $end
$upscope $end
$upscope $end
$scope module demux4_test $end
$var wire 1 B y3 $end
$var wire 1 C y2 $end
$var wire 1 D y1 $end
$var wire 1 E y0 $end
$var reg 1 F a $end
$var reg 1 G s0 $end
$var reg 1 H s1 $end
$scope module uut $end
$var wire 1 F a $end
$var wire 1 G s0 $end
$var wire 1 H s1 $end
$var wire 1 E y0 $end
$var wire 1 D y1 $end
$var wire 1 C y2 $end
$var wire 1 B y3 $end
$upscope $end
$upscope $end
$scope module demux8_test $end
$var wire 1 I y7 $end
$var wire 1 J y6 $end
$var wire 1 K y5 $end
$var wire 1 L y4 $end
$var wire 1 M y3 $end
$var wire 1 N y2 $end
$var wire 1 O y1 $end
$var wire 1 P y0 $end
$var reg 1 Q a $end
$var reg 1 R s0 $end
$var reg 1 S s1 $end
$var reg 1 T s2 $end
$scope module uut $end
$var wire 1 Q a $end
$var wire 1 R s0 $end
$var wire 1 S s1 $end
$var wire 1 T s2 $end
$var wire 1 P y0 $end
$var wire 1 O y1 $end
$var wire 1 N y2 $end
$var wire 1 M y3 $end
$var wire 1 L y4 $end
$var wire 1 K y5 $end
$var wire 1 J y6 $end
$var wire 1 I y7 $end
$upscope $end
$upscope $end
$scope module mux2_test $end
$var wire 1 U y $end
$var reg 1 V a $end
$var reg 1 W b $end
$var reg 1 X s $end
$scope module uut $end
$var wire 1 V a $end
$var wire 1 W b $end
$var wire 1 X s $end
$var wire 1 U y $end
$var wire 1 Y y1 $end
$var wire 1 Z y2 $end
$upscope $end
$upscope $end
$scope module mux4_test $end
$var wire 1 [ y $end
$var reg 1 \ a0 $end
$var reg 1 ] a1 $end
$var reg 1 ^ a2 $end
$var reg 1 _ a3 $end
$var reg 1 ` s0 $end
$var reg 1 a s1 $end
$scope module uut $end
$var wire 1 \ a0 $end
$var wire 1 ] a1 $end
$var wire 1 ^ a2 $end
$var wire 1 _ a3 $end
$var wire 1 ` s0 $end
$var wire 1 a s1 $end
$var wire 1 b y2 $end
$var wire 1 c y1 $end
$var wire 1 [ y $end
$scope module A1 $end
$var wire 1 \ a $end
$var wire 1 ] b $end
$var wire 1 ` s $end
$var wire 1 c y $end
$var wire 1 d y1 $end
$var wire 1 e y2 $end
$upscope $end
$scope module A2 $end
$var wire 1 ^ a $end
$var wire 1 _ b $end
$var wire 1 ` s $end
$var wire 1 b y $end
$var wire 1 f y1 $end
$var wire 1 g y2 $end
$upscope $end
$scope module A3 $end
$var wire 1 c a $end
$var wire 1 b b $end
$var wire 1 a s $end
$var wire 1 [ y $end
$var wire 1 h y1 $end
$var wire 1 i y2 $end
$upscope $end
$upscope $end
$upscope $end
$scope module mux8_test $end
$var wire 1 j y $end
$var reg 1 k a0 $end
$var reg 1 l a1 $end
$var reg 1 m a2 $end
$var reg 1 n a3 $end
$var reg 1 o a4 $end
$var reg 1 p a5 $end
$var reg 1 q a6 $end
$var reg 1 r a7 $end
$var reg 1 s s0 $end
$var reg 1 t s1 $end
$var reg 1 u s2 $end
$scope module uut $end
$var wire 1 k a0 $end
$var wire 1 l a1 $end
$var wire 1 m a2 $end
$var wire 1 n a3 $end
$var wire 1 o a4 $end
$var wire 1 p a5 $end
$var wire 1 q a6 $end
$var wire 1 r a7 $end
$var wire 1 s s0 $end
$var wire 1 t s1 $end
$var wire 1 u s2 $end
$var wire 1 v y2 $end
$var wire 1 w y1 $end
$var wire 1 j y $end
$scope module A1 $end
$var wire 1 k a0 $end
$var wire 1 l a1 $end
$var wire 1 m a2 $end
$var wire 1 n a3 $end
$var wire 1 s s0 $end
$var wire 1 t s1 $end
$var wire 1 x y2 $end
$var wire 1 y y1 $end
$var wire 1 w y $end
$scope module A1 $end
$var wire 1 k a $end
$var wire 1 l b $end
$var wire 1 s s $end
$var wire 1 y y $end
$var wire 1 z y1 $end
$var wire 1 { y2 $end
$upscope $end
$scope module A2 $end
$var wire 1 m a $end
$var wire 1 n b $end
$var wire 1 s s $end
$var wire 1 x y $end
$var wire 1 | y1 $end
$var wire 1 } y2 $end
$upscope $end
$scope module A3 $end
$var wire 1 y a $end
$var wire 1 x b $end
$var wire 1 t s $end
$var wire 1 w y $end
$var wire 1 ~ y1 $end
$var wire 1 !" y2 $end
$upscope $end
$upscope $end
$scope module A2 $end
$var wire 1 o a0 $end
$var wire 1 p a1 $end
$var wire 1 q a2 $end
$var wire 1 r a3 $end
$var wire 1 s s0 $end
$var wire 1 t s1 $end
$var wire 1 "" y2 $end
$var wire 1 #" y1 $end
$var wire 1 v y $end
$scope module A1 $end
$var wire 1 o a $end
$var wire 1 p b $end
$var wire 1 s s $end
$var wire 1 #" y $end
$var wire 1 $" y1 $end
$var wire 1 %" y2 $end
$upscope $end
$scope module A2 $end
$var wire 1 q a $end
$var wire 1 r b $end
$var wire 1 s s $end
$var wire 1 "" y $end
$var wire 1 &" y1 $end
$var wire 1 '" y2 $end
$upscope $end
$scope module A3 $end
$var wire 1 #" a $end
$var wire 1 "" b $end
$var wire 1 t s $end
$var wire 1 v y $end
$var wire 1 (" y1 $end
$var wire 1 )" y2 $end
$upscope $end
$upscope $end
$scope module A3 $end
$var wire 1 w a $end
$var wire 1 v b $end
$var wire 1 u s $end
$var wire 1 j y $end
$var wire 1 *" y1 $end
$var wire 1 +" y2 $end
$upscope $end
$upscope $end
$upscope $end
$enddefinitions $end
$comment Show the parameter values. $end
$dumpall
$end
#0
$dumpvars
0+"
1*"
0)"
1("
0'"
0&"
0%"
1$"
1#"
0""
0!"
1~
0}
1|
0{
1z
1y
1x
1w
1v
0u
0t
0s
0r
0q
1p
1o
0n
1m
0l
1k
1j
0i
0h
0g
0f
0e
0d
0c
0b
0a
0`
1_
0^
1]
0\
0[
0Z
0Y
0X
1W
0V
0U
0T
0S
0R
0Q
0P
0O
0N
0M
0L
0K
0J
0I
0H
0G
0F
0E
0D
0C
0B
0A
0@
0?
0>
0=
0<
1;
0:
19
08
07
06
15
04
03
02
01
00
0/
0.
0-
0,
0+
0*
0)
0(
0'
0&
0%
0$
0#
0"
0!
$end
#5
1R
1G
1A
#10
1?
05
14
0R
0G
0A
1S
1H
1@
18
1*
1#
#15
0?
1>
1R
1G
1A
#20
0j
0*"
0w
0~
0y
0x
1E
1"
0z
0|
0$"
0;
13
0>
04
1%"
1:
0R
0G
0A
0S
0H
0@
08
0*
0#
1s
1a
1T
1F
17
1)
1$
#25
0E
1D
1R
1G
1A
#30
1C
1?
03
0"
0D
12
1!
0R
0G
0A
1S
1H
1@
18
1*
1#
#35
0C
0?
1B
1>
1R
1G
1A
#40
1j
1*"
1w
1!"
0v
1y
1x
1[
11
1(
0("
1z
1|
1$"
1#"
1h
1c
1b
1P
1=
1-
0>
02
0%"
1e
1g
0B
0:
0!
09
0R
0G
0A
0S
0H
0@
08
0*
0#
1t
0s
0a
1`
0T
0F
07
0)
0$
1Q
16
1+
#45
0P
1O
1R
1G
1A
#50
1N
1?
01
0(
1U
0O
10
1'
1Z
0R
0G
0A
1S
1H
1@
18
1*
1#
1X
#55
0N
0?
1M
1>
1R
1G
1A
#60
0j
0*"
0w
0!"
0y
0x
1L
1E
1"
0z
0|
0$"
0h
0=
1/
0-
1&
0M
0>
00
0'
1%"
1i
1<
1,
0R
0G
0A
0S
0H
0@
08
0*
0#
1s
1a
1T
1F
17
1)
1$
#65
0L
0E
1K
1D
1R
1G
1A
#70
1J
1C
1?
0/
0&
0"
0K
0D
1.
1%
1!
0R
0G
0A
1S
1H
1@
18
1*
1#
#75
0J
0C
0?
1I
1B
1>
1R
1G
1A
#80
1j
1+"
1w
1v
1~
1("
1y
1x
15
1z
1|
1$"
1#"
1;
0>
0.
0%
0%"
0B
0!
0I
19
0<
0,
0R
0G
0A
0S
0H
0@
08
0*
0#
1u
0t
0s
0T
0F
07
0)
0$
0Q
06
0+
